CHANGES.rst
LICENSE
MANIFEST.in
README.rst
setup.py
nose_notify.egg-info/PKG-INFO
nose_notify.egg-info/SOURCES.txt
nose_notify.egg-info/dependency_links.txt
nose_notify.egg-info/entry_points.txt
nose_notify.egg-info/top_level.txt
nosenotify/__init__.py
nosenotify/adapters.py
nosenotify/plugin.py
nosenotify/images/dialog-cancel.png
nosenotify/images/dialog-ok.png