Metadata-Version: 1.1
Name: nose-notify
Version: 0.4.2
Summary: A nose plugin to display testsuite progress in the notify osd
Home-page: https://github.com/passy/nose-notify
Author: Pascal Hartig
Author-email: phartig@rdrei.de
License: UNKNOWN
Platform: UNKNOWN
Classifier: Development Status :: 4 - Beta
Classifier: Intended Audience :: Developers
Classifier: Programming Language :: Python :: 2.6
Classifier: Programming Language :: Python :: 2.7
Classifier: Programming Language :: Python :: 3
Classifier: Topic :: Software Development :: Testing
Classifier: Topic :: Software Development :: Libraries :: Python Modules
Requires: nose (>=0.10)
